Workbook

Sheet customers
A1: customer_id | B1: customer_name | C1: city | D1: state | E1: age | F1: gender | G1: Duplicate_Check
A2: C001 | B2: Rahul X. | C2: Tirupati | D2: Andhra Pradesh | E2: 35 | F2: Male | G2: =COUNTIF(A:A,A2) -> 1
A3: C002 | B3: Arjun X. | C3: Mumbai | D3: Maharashtra | E3: 24 | F3: Male | G3: =COUNTIF(A:A,A3) -> 1
A4: C003 | B4: Kavya B. | C4: Coimbatore | D4: Tamil Nadu | E4: 19 | F4: Male | G4: =COUNTIF(A:A,A4) -> 1
A5: C004 | B5: Pooja Q. | C5: Bengaluru | D5: Karnataka | E5: 56 | F5: Male | G5: =COUNTIF(A:A,A5) -> 1
A6: C005 | B6: Ravi W. | C6: Bhubaneswar | D6: Odisha | E6: 59 | F6: Female | G6: =COUNTIF(A:A,A6) -> 1
A7: C006 | B7: Rohit S. | C7: Mumbai | D7: Maharashtra | E7: 35 | F7: Male | G7: =COUNTIF(A:A,A7) -> 1
A8: C007 | B8: Kavya K. | C8: Chennai | D8: Tamil Nadu | E8: 35 | F8: Male | G8: =COUNTIF(A:A,A8) -> 1
A9: C008 | B9: Suresh D. | C9: Bengaluru | D9: Karnataka | E9: 23 | F9: Female | G9: =COUNTIF(A:A,A9) -> 1
A10: C009 | B10: Neha L. | C10: Tirupati | D10: Andhra Pradesh | E10: 56 | F10: Female | G10: =COUNTIF(A:A,A10) -> 1
A11: C010 | B11: Rohit R. | C11: Vijayawada | D11: Andhra Pradesh | E11: 25 | F11: Female | G11: =COUNTIF(A:A,A11) -> 1
A12: C011 | B12: Lakshmi J. | C12: Visakhapatnam | D12: Andhra Pradesh | E12: 58 | F12: Female | G12: =COUNTIF(A:A,A12) -> 1
A13: C012 | B13: Ravi W. | C13: Coimbatore | D13: Tamil Nadu | E13: 22 | F13: Male | G13: =COUNTIF(A:A,A13) -> 1
... A501: C500 | B501: Arjun I. | C501: Kochi | D501: Kerala | E501: 30 | F501: Male | G501: =COUNTIF(A:A,A501) -> 1

Sheet products
A1: product_id | B1: product_name | C1: category | D1: price | E1: cost
A2: 1 | B2: Laptop | C2: Electronics | D2: 637 | E2: 359.91
A3: 2 | B3: Mobile | C3: Electronics | D3: 774 | E3: 448.92
A4: 3 | B4: Headphones | C4: Electronics | D4: 911 | E4: 542.05
A5: 4 | B5: Smart Watch | C5: Electronics | D5: 1048 | E5: 639.28
A6: 5 | B6: Keyboard | C6: Electronics | D6: 1185 | E6: 740.62
A7: 6 | B7: Mouse | C7: Electronics | D7: 1322 | E7: 846.08
A8: 7 | B8: Monitor | C8: Electronics | D8: 1459 | E8: 955.65
A9: 8 | B9: Tablet | C9: Electronics | D9: 1596 | E9: 1069.32
A10: 9 | B10: Power Bank | C10: Electronics | D10: 1733 | E10: 1187.11
A11: 10 | B11: Earbuds | C11: Electronics | D11: 1870 | E11: 1028.5
A12: 11 | B12: T-Shirt | C12: Fashion | D12: 2007 | E12: 1133.96
A13: 12 | B13: Jeans | C13: Fashion | D13: 2144 | E13: 1243.52
... A51: 50 | B51: Building Blocks | C51: Toys | D51: 7350 | E51: 4042.5

Sheet orders
A1: order_id | B1: customer_id | C1: order_date | D1: order_status | E1: order_month
A2: 101 | B2: 1 | C2: 45658 | D2: Delivered | E2: =TEXT(Table3[[#This Row],[order_date]],"mmm-yyyy") -> Jan-2025
A3: 102 | B3: 38 | C3: 45661 | D3: Delivered | E3: =TEXT(Table3[[#This Row],[order_date]],"mmm-yyyy") -> Jan-2025
A4: 103 | B4: 75 | C4: 45664 | D4: Pending | E4: =TEXT(Table3[[#This Row],[order_date]],"mmm-yyyy") -> Jan-2025
A5: 104 | B5: 112 | C5: 45667 | D5: Delivered | E5: =TEXT(Table3[[#This Row],[order_date]],"mmm-yyyy") -> Jan-2025
A6: 105 | B6: 149 | C6: 45670 | D6: Delivered | E6: =TEXT(Table3[[#This Row],[order_date]],"mmm-yyyy") -> Jan-2025
A7: 106 | B7: 186 | C7: 45673 | D7: Delivered | E7: =TEXT(Table3[[#This Row],[order_date]],"mmm-yyyy") -> Jan-2025
A8: 107 | B8: 223 | C8: 45676 | D8: Delivered | E8: =TEXT(Table3[[#This Row],[order_date]],"mmm-yyyy") -> Jan-2025
A9: 108 | B9: 260 | C9: 45679 | D9: Pending | E9: =TEXT(Table3[[#This Row],[order_date]],"mmm-yyyy") -> Jan-2025
A10: 109 | B10: 297 | C10: 45682 | D10: Delivered | E10: =TEXT(Table3[[#This Row],[order_date]],"mmm-yyyy") -> Jan-2025
A11: 110 | B11: 334 | C11: 45685 | D11: Delivered | E11: =TEXT(Table3[[#This Row],[order_date]],"mmm-yyyy") -> Jan-2025
A12: 111 | B12: 371 | C12: 45688 | D12: Delivered | E12: =TEXT(Table3[[#This Row],[order_date]],"mmm-yyyy") -> Jan-2025
A13: 112 | B13: 408 | C13: 45691 | D13: Delivered | E13: =TEXT(Table3[[#This Row],[order_date]],"mmm-yyyy") -> Feb-2025
... A501: 600 | B501: 464 | C501: 45695 | D501: Delivered | E501: =TEXT(Table3[[#This Row],[order_date]],"mmm-yyyy") -> Feb-2025

Sheet order_items
A1: order_item_id | B1: order_id | C1: product_id | D1: quantity | E1: unit_price | F1: revenue | G1: profit | H1: category | I1: product_name | J1: order_date | K1: order_month | L1: customer_id | M1: customer_name
A2: 1 | B2: 101 | C2: 8 | D2: 2 | E2: =_xlfn.XLOOKUP(C2,products!A:A,products!D:D) -> 1596 | F2: =D2*E2 -> 3192 | G2: =D2*(E2-_xlfn.XLOOKUP(C2,products!A:A,products!E:E)) -> 1053.36 | H2: =_xlfn.XLOOKUP(C2,products!A:A,products!C:C) -> Electronics | I2: =_xlfn.XLOOKUP(C2,products!A:A,products!B:B) -> Tablet | J2: =_xlfn.XLOOKUP(B2,orders!A:A,orders!C:C) -> 45658 | K2: =TEXT(J2,"mmm-yyyy") -> Jan-2025 | L2: =_xlfn.XLOOKUP(B2,orders!A:A,orders!B:B) -> 1 | M2: =_xlfn.XLOOKUP("C"&TEXT(L2,"000"),customers!A:A,customers!B:B,"Not Found") -> Rahul X.
A3: 2 | B3: 101 | C3: 21 | D3: 3 | E3: =_xlfn.XLOOKUP(C3,products!A:A,products!D:D) -> 3377 | F3: =D3*E3 -> 10131 | G3: =D3*(E3-_xlfn.XLOOKUP(C3,products!A:A,products!E:E)) -> 4406.97 | H3: =_xlfn.XLOOKUP(C3,products!A:A,products!C:C) -> Home Appliances | I3: =_xlfn.XLOOKUP(C3,products!A:A,products!B:B) -> Mixer | J3: =_xlfn.XLOOKUP(B3,orders!A:A,orders!C:C) -> 45658 | K3: =TEXT(J3,"mmm-yyyy") -> Jan-2025 | L3: =_xlfn.XLOOKUP(B3,orders!A:A,orders!B:B) -> 1 | M3: =_xlfn.XLOOKUP("C"&TEXT(L3,"000"),customers!A:A,customers!B:B,"Not Found") -> Rahul X.
A4: 3 | B4: 102 | C4: 15 | D4: 3 | E4: =_xlfn.XLOOKUP(C4,products!A:A,products!D:D) -> 2555 | F4: =D4*E4 -> 7665 | G4: =D4*(E4-_xlfn.XLOOKUP(C4,products!A:A,products!E:E)) -> 2874.36 | H4: =_xlfn.XLOOKUP(C4,products!A:A,products!C:C) -> Fashion | I4: =_xlfn.XLOOKUP(C4,products!A:A,products!B:B) -> Shoes | J4: =_xlfn.XLOOKUP(B4,orders!A:A,orders!C:C) -> 45661 | K4: =TEXT(J4,"mmm-yyyy") -> Jan-2025 | L4: =_xlfn.XLOOKUP(B4,orders!A:A,orders!B:B) -> 38 | M4: =_xlfn.XLOOKUP("C"&TEXT(L4,"000"),customers!A:A,customers!B:B,"Not Found") -> Neha O.
A5: 4 | B5: 102 | C5: 28 | D5: 4 | E5: =_xlfn.XLOOKUP(C5,products!A:A,products!D:D) -> 4336 | F5: =D5*E5 -> 17344 | G5: =D5*(E5-_xlfn.XLOOKUP(C5,products!A:A,products!E:E)) -> 5723.52 | H5: =_xlfn.XLOOKUP(C5,products!A:A,products!C:C) -> Home & Kitchen | I5: =_xlfn.XLOOKUP(C5,products!A:A,products!B:B) -> Bottle | J5: =_xlfn.XLOOKUP(B5,orders!A:A,orders!C:C) -> 45661 | K5: =TEXT(J5,"mmm-yyyy") -> Jan-2025 | L5: =_xlfn.XLOOKUP(B5,orders!A:A,orders!B:B) -> 38 | M5: =_xlfn.XLOOKUP("C"&TEXT(L5,"000"),customers!A:A,customers!B:B,"Not Found") -> Neha O.
A6: 5 | B6: 103 | C6: 22 | D6: 4 | E6: =_xlfn.XLOOKUP(C6,products!A:A,products!D:D) -> 3514 | F6: =D6*E6 -> 14056 | G6: =D6*(E6-_xlfn.XLOOKUP(C6,products!A:A,products!E:E)) -> 5903.52 | H6: =_xlfn.XLOOKUP(C6,products!A:A,products!C:C) -> Home Appliances | I6: =_xlfn.XLOOKUP(C6,products!A:A,products!B:B) -> Microwave | J6: =_xlfn.XLOOKUP(B6,orders!A:A,orders!C:C) -> 45664 | K6: =TEXT(J6,"mmm-yyyy") -> Jan-2025 | L6: =_xlfn.XLOOKUP(B6,orders!A:A,orders!B:B) -> 75 | M6: =_xlfn.XLOOKUP("C"&TEXT(L6,"000"),customers!A:A,customers!B:B,"Not Found") -> Rahul K.
A7: 6 | B7: 103 | C7: 35 | D7: 1 | E7: =_xlfn.XLOOKUP(C7,products!A:A,products!D:D) -> 5295 | F7: =D7*E7 -> 5295 | G7: =D7*(E7-_xlfn.XLOOKUP(C7,products!A:A,products!E:E)) -> 1985.62 | H7: =_xlfn.XLOOKUP(C7,products!A:A,products!C:C) -> Books | I7: =_xlfn.XLOOKUP(C7,products!A:A,products!B:B) -> Novel | J7: =_xlfn.XLOOKUP(B7,orders!A:A,orders!C:C) -> 45664 | K7: =TEXT(J7,"mmm-yyyy") -> Jan-2025 | L7: =_xlfn.XLOOKUP(B7,orders!A:A,orders!B:B) -> 75 | M7: =_xlfn.XLOOKUP("C"&TEXT(L7,"000"),customers!A:A,customers!B:B,"Not Found") -> Rahul K.
A8: 7 | B8: 104 | C8: 29 | D8: 1 | E8: =_xlfn.XLOOKUP(C8,products!A:A,products!D:D) -> 4473 | F8: =D8*E8 -> 4473 | G8: =D8*(E8-_xlfn.XLOOKUP(C8,products!A:A,products!E:E)) -> 1408.99 | H8: =_xlfn.XLOOKUP(C8,products!A:A,products!C:C) -> Furniture | I8: =_xlfn.XLOOKUP(C8,products!A:A,products!B:B) -> Chair | J8: =_xlfn.XLOOKUP(B8,orders!A:A,orders!C:C) -> 45667 | K8: =TEXT(J8,"mmm-yyyy") -> Jan-2025 | L8: =_xlfn.XLOOKUP(B8,orders!A:A,orders!B:B) -> 112 | M8: =_xlfn.XLOOKUP("C"&TEXT(L8,"000"),customers!A:A,customers!B:B,"Not Found") -> Meena X.
A9: 8 | B9: 104 | C9: 42 | D9: 2 | E9: =_xlfn.XLOOKUP(C9,products!A:A,products!D:D) -> 6254 | F9: =D9*E9 -> 12508 | G9: =D9*(E9-_xlfn.XLOOKUP(C9,products!A:A,products!E:E)) -> 5253.36 | H9: =_xlfn.XLOOKUP(C9,products!A:A,products!C:C) -> Beauty | I9: =_xlfn.XLOOKUP(C9,products!A:A,products!B:B) -> Shampoo | J9: =_xlfn.XLOOKUP(B9,orders!A:A,orders!C:C) -> 45667 | K9: =TEXT(J9,"mmm-yyyy") -> Jan-2025 | L9: =_xlfn.XLOOKUP(B9,orders!A:A,orders!B:B) -> 112 | M9: =_xlfn.XLOOKUP("C"&TEXT(L9,"000"),customers!A:A,customers!B:B,"Not Found") -> Meena X.
A10: 9 | B10: 105 | C10: 36 | D10: 2 | E10: =_xlfn.XLOOKUP(C10,products!A:A,products!D:D) -> 5432 | F10: =D10*E10 -> 10864 | G10: =D10*(E10-_xlfn.XLOOKUP(C10,products!A:A,products!E:E)) -> 3911.04 | H10: =_xlfn.XLOOKUP(C10,products!A:A,products!C:C) -> Sports | I10: =_xlfn.XLOOKUP(C10,products!A:A,products!B:B) -> Cricket Bat | J10: =_xlfn.XLOOKUP(B10,orders!A:A,orders!C:C) -> 45670 | K10: =TEXT(J10,"mmm-yyyy") -> Jan-2025 | L10: =_xlfn.XLOOKUP(B10,orders!A:A,orders!B:B) -> 149 | M10: =_xlfn.XLOOKUP("C"&TEXT(L10,"000"),customers!A:A,customers!B:B,"Not Found") -> Ravi L.
A11: 10 | B11: 105 | C11: 49 | D11: 3 | E11: =_xlfn.XLOOKUP(C11,products!A:A,products!D:D) -> 7213 | F11: =D11*E11 -> 21639 | G11: =D11*(E11-_xlfn.XLOOKUP(C11,products!A:A,products!E:E)) -> 6816.27 | H11: =_xlfn.XLOOKUP(C11,products!A:A,products!C:C) -> Toys | I11: =_xlfn.XLOOKUP(C11,products!A:A,products!B:B) -> Remote Car | J11: =_xlfn.XLOOKUP(B11,orders!A:A,orders!C:C) -> 45670 | K11: =TEXT(J11,"mmm-yyyy") -> Jan-2025 | L11: =_xlfn.XLOOKUP(B11,orders!A:A,orders!B:B) -> 149 | M11: =_xlfn.XLOOKUP("C"&TEXT(L11,"000"),customers!A:A,customers!B:B,"Not Found") -> Ravi L.
A12: 11 | B12: 106 | C12: 43 | D12: 3 | E12: =_xlfn.XLOOKUP(C12,products!A:A,products!D:D) -> 6391 | F12: =D12*E12 -> 19173 | G12: =D12*(E12-_xlfn.XLOOKUP(C12,products!A:A,products!E:E)) -> 7765.05 | H12: =_xlfn.XLOOKUP(C12,products!A:A,products!C:C) -> Beauty | I12: =_xlfn.XLOOKUP(C12,products!A:A,products!B:B) -> Perfume | J12: =_xlfn.XLOOKUP(B12,orders!A:A,orders!C:C) -> 45673 | K12: =TEXT(J12,"mmm-yyyy") -> Jan-2025 | L12: =_xlfn.XLOOKUP(B12,orders!A:A,orders!B:B) -> 186 | M12: =_xlfn.XLOOKUP("C"&TEXT(L12,"000"),customers!A:A,customers!B:B,"Not Found") -> Nikhil A.
A13: 12 | B13: 106 | C13: 6 | D13: 4 | E13: =_xlfn.XLOOKUP(C13,products!A:A,products!D:D) -> 1322 | F13: =D13*E13 -> 5288 | G13: =D13*(E13-_xlfn.XLOOKUP(C13,products!A:A,products!E:E)) -> 1903.68 | H13: =_xlfn.XLOOKUP(C13,products!A:A,products!C:C) -> Electronics | I13: =_xlfn.XLOOKUP(C13,products!A:A,products!B:B) -> Mouse | J13: =_xlfn.XLOOKUP(B13,orders!A:A,orders!C:C) -> 45673 | K13: =TEXT(J13,"mmm-yyyy") -> Jan-2025 | L13: =_xlfn.XLOOKUP(B13,orders!A:A,orders!B:B) -> 186 | M13: =_xlfn.XLOOKUP("C"&TEXT(L13,"000"),customers!A:A,customers!B:B,"Not Found") -> Nikhil A.
... A1001: 1000 | B1001: 600 | C1001: 14 | D1001: 2 | E1001: =_xlfn.XLOOKUP(C1001,products!A:A,products!D:D) -> 2418 | F1001: =D1001*E1001 -> 4836 | G1001: =D1001*(E1001-_xlfn.XLOOKUP(C1001,products!A:A,products!E:E)) -> 1886.04 | H1001: =_xlfn.XLOOKUP(C1001,products!A:A,products!C:C) -> Fashion | I1001: =_xlfn.XLOOKUP(C1001,products!A:A,products!B:B) -> Jacket | J1001: =_xlfn.XLOOKUP(B1001,orders!A:A,orders!C:C) -> 45695 | K1001: =TEXT(J1001,"mmm-yyyy") -> Feb-2025 | L1001: =_xlfn.XLOOKUP(B1001,orders!A:A,orders!B:B) -> 464 | M1001: =_xlfn.XLOOKUP("C"&TEXT(L1001,"000"),customers!A:A,customers!B:B,"Not Found") -> Priya Y.

Sheet payments
A1: payment_id | B1: order_id | C1: payment_date | D1: payment_method | E1: payment_status | F1: amount
A2: 1 | B2: 101 | C2: 45658 | D2: UPI | E2: Paid | F2: 13323
A3: 2 | B3: 102 | C3: 45661 | D3: Credit Card | E3: Paid | F3: 25009
A4: 3 | B4: 103 | C4: 45664 | D4: Debit Card | E4: Paid | F4: 19351
A5: 4 | B5: 104 | C5: 45667 | D5: Net Banking | E5: Paid | F5: 16981
A6: 5 | B6: 105 | C6: 45670 | D6: Cash on Delivery | E6: Paid | F6: 32503
A7: 6 | B7: 106 | C7: 45673 | D7: UPI | E7: Paid | F7: 24461
A8: 7 | B8: 107 | C8: 45676 | D8: Credit Card | E8: Paid | F8: 31681
A9: 8 | B9: 108 | C9: 45679 | D9: Debit Card | E9: Paid | F9: 7939
A10: 9 | B10: 109 | C10: 45682 | D10: Net Banking | E10: Paid | F10: 17433
A11: 10 | B11: 110 | C11: 45685 | D11: Cash on Delivery | E11: Paid | F11: 30763
A12: 11 | B12: 111 | C12: 45688 | D12: UPI | E12: Paid | F12: 23461
A13: 12 | B13: 112 | C13: 45691 | D13: Credit Card | E13: Paid | F13: 19447
... A501: 500 | B501: 600 | C501: 45695 | D501: Cash on Delivery | E501: Paid | F501: 5473

Sheet payment_method_analysis
A3: payment_method | B3: Sum of payment_id | C3: Sum of amount
A4: Cash on Delivery | B4: 25250 | C4: 1962500
A5: Credit Card | B5: 24950 | C5: 2099500
A6: Debit Card | B6: 25050 | C6: 2031000
A7: Net Banking | B7: 25150 | C7: 1962500
A8: UPI | B8: 24850 | C8: 1962500
A9: Grand Total | B9: 125250 | C9: 10018000

Sheet customer_wise_revenue
A3: customer_name | B3: Sum of revenue
A4: Divya V. | B4: 160028
A5: Priya J. | B5: 101317
A6: Priya B. | B6: 99783
A7: Suresh D. | B7: 91207
A8: Rohit L. | B8: 90933
A9: Kavya L. | B9: 86083
A10: Vikram O. | B10: 81966
A11: Swathi Q. | B11: 79500
A12: Arjun E. | B12: 79425
A13: Sneha Z. | B13: 76582
A14: Grand Total | B14: 946824

Sheet E-COMMERCE SALES ANALYTICS DASH
A1: E-COMMERCE SALES ANALYTICS DASHBOARD
A3: Total Revenue | D3: Total Orders | G3: Total Customers | J3: Total Profit
A4: =SUM(order_items!F:F) -> 10018000 | D4: =COUNTA(orders!A:A)-1 -> 500 | G4: =COUNTA(customers!A:A)-1 -> 500 | J4: =SUM(order_items!G:G) -> 3831701.2

Sheet category_wise_revenue
A3: category | B3: Sum of revenue
A4: Toys | B4: 1839760
A5: Beauty | B5: 1533840
A6: Sports | B6: 1483560
A7: Fashion | B7: 1318600
A8: Books | B8: 1205040
A9: Home Appliances | B9: 876240
A10: Home & Kitchen | B10: 671840
A11: Electronics | B11: 633600
A12: Furniture | B12: 455520
A13: Grand Total | B13: 10018000

Sheet top-10_products_by_revenue
A3: product_name | B3: Sum of revenue
A4: Building Blocks | B4: 441000
A5: Board Game | B5: 424560
A6: Toys Car | B6: 408120
A7: Moisturizer | B7: 391680
A8: Shampoo | B8: 375240
A9: Dumbbells | B9: 358800
A10: Badminton Racket | B10: 342360
A11: Cricket Bat | B11: 325920
A12: Cookbook | B12: 309480
A13: Notebook | B13: 293040
A14: Grand Total | B14: 3670200

Sheet monthly_revenue
A3: order_month | B3: Sum of revenue
A4: Apr-2025 | B4: 852596
A5: Aug-2025 | B5: 771745
A6: Dec-2025 | B6: 757675
A7: Feb-2025 | B7: 831580
A8: Jan-2025 | B8: 1073930
A9: Jul-2025 | B9: 850109
A10: Jun-2025 | B10: 838704
A11: Mar-2025 | B11: 752195
A12: May-2025 | B12: 789630
A13: Nov-2025 | B13: 859446
A14: Oct-2025 | B14: 792644
A15: Sep-2025 | B15: 847746
A16: Grand Total | B16: 10018000
